{
  "type": "object",
  "properties": {
    "type": {
      "type": "string"
    },
    "title": {
      "type": "object",
      "properties": {
        "et": {
          "type": "string",
          "minLength": 1
        }
      },
      "required": [
        "et"
      ]
    },
    "helpertext": {
      "type": "object",
      "properties": {
        "et": {
          "type": "string",
          "minLength": 1
        }
      },
      "required": [
        "et"
      ]
    },
    "default_value": {
      "type": "string"
    },
    "width": {
      "type": "integer"
    },
    "acceptable_extensions": {
      "type": "array",
      "items": {
        "type": "string"
      }
    },
    "multiple": {
      "type": "boolean"
    },
    "readonly": {
      "type": "boolean"
    },
    "hidden": {
      "type": "boolean"
    },
    "required": {
      "type": "boolean"
    },
    "max_size": {
      "type": "integer"
    },
    "depend_on": {
      "type": "string"
    },
    "submit_on_change": {
      "type": "boolean"
    }
  },
  "required": [
    "type",
    "title"
  ],
  "additionalProperties": false
}
