{
  "frontpage": {
    "label": "Home",
    "navigate": "Go to homepage",
    "favourites_limit_modal_title": "Add to favourites",
    "favourites_limit_modal_content": "You can add up to 10 favourites. Remove page from favourites by clicking on the star icon of already favourited page.",
    "favourites_limit_modal_close": "Close",
    "favourites_list_label" : "My favourites",
    "favourites_list_none_message" : "You don't have any favourites added. You can do so by clicking on the star icon on topic pages and lists.",
    "favourites_snackbar_message": "This page has been added to favourites. Favourites can be viewed from the Dashboard.",
    "favourites_snackbar_message_remove": "This page has been removed from favourites.",
    "favourites_snackbar_action": "Show dashboard",
    "dashboard_label": "Dashboard",
    "dashboard_tabs_applications": "Applications",
    "dashboard_tabs_certificates":"Certificates",
    "dashboard_tabs_studies":"Studies",
    "dashboard_tabs_teachings":"Teachings",
    "dashboard_tabs_certificates_no_results": "No certificates.",
    "dashboard_tabs_certificates_error_technical":"Sorry, a technical error has occurred. Please try again later.",
    "dashboard_tabs_certificates_professional": "Professional certificates",
    "dashboard_tabs_certificates_examinations": "State examinations",
    "dashboard_tabs_certificates_number":"Certificate number",
    "dashboard_tabs_certificates_name":"Certificate name",
    "dashboard_tabs_certificates_type":"Type",
    "dashboard_tabs_certificates_standard":"Standard",
    "dashboard_tabs_certificates_ekr":"EKR level",
    "dashboard_tabs_certificates_eqf":"EQF level",
    "dashboard_tabs_certificates_specialization":"Specialization",
    "dashboard_tabs_certificates_part":"Part of vocation",
    "dashboard_tabs_certificates_competence":"Competence",
    "dashboard_tabs_certificates_field":"Field",
    "dashboard_tabs_certificates_field_topic":"Topic",
    "dashboard_tabs_certificates_qualification":"Academic qualification",
    "dashboard_tabs_certificates_language":"Examination language",
    "dashboard_tabs_certificates_issuer":"Issuer",
    "dashboard_tabs_certificates_issued_at":"Issued at",
    "dashboard_tabs_certificates_valid_from":"Valid from",
    "dashboard_tabs_certificates_valid_to":"Valid to",
    "dashboard_tabs_certificates_isco":"Profession classification (ISCO)",
    "dashboard_tabs_certificates_duplicate":"Duplicate",
    "dashboard_tabs_certificates_notvalid":"Invalid",
    "dashboard_tabs_personal_label":"Personal data",
    "isikukood": "ID code",
    "synniKp": "Date of birth",
    "elukohamaa": "Nation",
    "rrElukoht": "Residence in registry",
    "kodakondsus": "Nationality",
    "elamisluba": "Permit of residence",
    "oppelaenOigus": "Loan privileges",
    "reason": "Reason",
    "studies_data": "Õpingute andmed-ENG",
    "teachings_data": "Õpetamiste andmed-ENG",
    "oppeasutus": "Õppeasutus-ENG",
    "haridustase": "Haridustase-ENG",
    "oppekava": "Õppekava(d)-ENG",
    "oppekeel": "Õppekeel-ENG",
    "opeklass": "Õpe/klass-ENG",
    "opeParallel": "Paralleeli tunnus-ENG",
    "klassiLiik": "Klassi liik-ENG",
    "klassAste": "Kooliaste-ENG",
    "oppAlgus": "Õppimise alguse-ENG",
    "oppLopp": "Õppimise lõpp-ENG",
    "staatus": "Staatus-ENG",
    "tunnistusDiplom": "Tunnistuse/Diplomi number-ENG",
    "oppevorm": "Õppevorm-ENG",
    "koormus": "Õppekoormus-ENG",
    "kestus": "Õppekava järgne nominaalkestus-ENG",
    "ryhmaLiik": "Rühma liik-ENG",
    "ryhmaNimetus": "Rühma nimetus-ENG",
    "koht": "Osakoha suurus-ENG",
    "finAllikas": "Finantseerimise allikas-ENG",
    "akadPuhkus": "Akadeemiline puhkus-ENG",
    "ennistamine": "Ennistamine-ENG",
    "puudumised": "Põhjuseta puudumised eelmisel õppeveerandil (%)-ENG",
    "kutseKoolitus": "Kutsealane eelkoolitus-ENG",
    "oppekavaKood": "Õppekava kood-ENG",
    "oppekavaNimetus": "Õppekava nimetus-ENG",
    "nimetus": "Nimetus-ENG",
    "algusKp": "Alguskuupäev-ENG",
    "loppKp": "Lõppkuupäev-ENG",
    "tootamine": "Pedagoogina ja õppejõuna töötamineENG",
    "kvalifikatsioon": "Õppejõu kvalifikatsioonENG",
    "tasemeharidus": "Tasemeharidus kvalifikatsioonENG",
    "taiendkoolitus": "TäiendkoolitusENG",
    "lead_title_xxs": "Hoia end<br> haridusinfoga kursis!ENG",
    "lead_title_sm": "Hoia end haridusinfoga kursis!ENG",
    "lead_title": "<b>Eduportaal -</b><br>hoia end haridusinfoga kursis!ENG",
    "ametikoht": "Ametikoht ENG",
    "ametikohtAlgus": "Töötamise algus ENG",
    "ametikohtLopp": "Töötamise lõpp ENG",
    "ametikohtKoormus": "Koormus ENG",
    "ametikohtKvalVastavus": "Kvalifikatsiooninõuetele vastavus ENG",
    "taitmiseViis": "Ametikoha täitmise viis ENG",
    "tooleping": "Tööleping ENG",
    "ametijark": "Ametijärk ENG",
    "oppeaine": "Õppeaine ENG",
    "lapsehooldusPuhkus": "lapsehoolduspuhkusel ENG",
    "dokument": "Dokument ENG",
    "kraadNimetus": "Kvalifikatsiooni/akadeemilise kraadi nimetus ENG",
    "kvalifikatsioonVastavus": "Vastavus kehtivas raamistikus ENG",
    "aasta": "Aasta ENG",
    "riik": "Riik ENG",
    "kvalDokument": "Kvalifikatsiooni dokument ENG",
    "kvalVastavus": "Kvalifikatsioon kehtivas raamistikus ENG",
    "erialaOppekava": "Eriala/õppekava ENG",
    "lopetanud": "Lõpetamise kuupäev ENG",
    "dokumentNr": "Dokumendi nr. ENG",
    "koolitusNimetus": "Koolituse nimetus ENG",
    "liik": "Liik ENG",
    "maht": "Maht ENG"
  },
  "xjson":{
    "edit_step_confirm_modal_content": "Changing data on this step could delete data from steps that follow. Are you sure you want to edit this step?"
  },
  "article": {
    "label": "Article",
    "contact": "Contact",
    "hyperlinks": "",
    "similar_articles": ""
  },
  "news": {
    "label": "News",
    "under": "All news",
    "recent": "Latest News",
    "filter_name": "Enter news name",
    "filter_tag": "News Tags",
    "title": "Title",
    "no_results": "No Search Results"
  },
  "newsletter": {
    "title": "Newsletter - order interesting stories",
    "intro": "Introduction",
    "confirm_subscription": "Confirm order",
    "Email": "Enter your email address",
    "valid_email": "Enter the correct email",
    "order_to_email": "Order to email",
    "modal_title": "ORDERING NEWSLETTER",
    "modal_content": "<p> Thank you for your interest in education! </ p> <p> You have successfully joined the newsletter. </ p>",
    "modal_close": "Close window",
    "unsubscribe_title": "NEW DISCLAIMER",
    "unsubscribe_content": "<p> Thank you for your interest in education. </ p> <br /> <p> You have abandoned the education newsletter. </ p> <span> Continue to visit the <a href = 'http: // www website. .eduportaal.ee 'target =' _ blank '> www.eduportaal.ee </a>. </ span> ",
    "subscription_thanks_content": "Thank you for your interest in education!",
    "subscription_thanks_subcontent": "We kindly ask you to sign up for a newsletter through the link we provided to the order-related email address",
    "subscription_choose_one": "Select at least one newsletter",
    "subscription_failed": "Delivery of the order failed"
  },
  "event": {
    "label": "Events",
    "tags": "Event Labels",
    "status": "Event status",
    "free": "Free",
    "register": "By registration",
    "invite": "With invitations",
    "practical_info": "Practical info",
    "passed": "The event has passed",
    "group": "Event Group",
    "list": "List",
    "calendar": "Calendar",
    "entrance": "Entrance",
    "related": "Similar events",
    "start_time": "Start time",
    "location": "Location",
    "repeat": "Repeatable event",
    "place_and_time": "time and place",
    "participant_email": "Email",
    "participant_phone": "Phone",
    "participant_last_name": "Surname",
    "participant_first_name": "First Name",
    "participant_organization": "Company / Institution",
    "participant_created": "Registration Time",
    "participant_comment": "Notes",
    "participant_index": "jrk no",
    "participant_list": "Participant List",
    "participant_count": "Participant",
    "participants_list_view": "View the list of participants",
    "filter_name": "Search by event name",
    "filter_tags": "Event labels",
    "filter_types": "Event Types",
    "filter_status": "Event Status",
    "contact": "Contact",
    "registration_form": "Registration Form",
    "registration_form_required": "Marked fields are required",
    "registration_form_valid_email": "Enter correct email",
    "registration_form_send": "Send",
    "registration_form_close": "Close window",
    "registration_form_cancel": "Cancel",
    "registration_form_thanks": "Thank you for registering for an event!",
    "registration_form_add_to_calendar": "Add event to your own calendar (iCal)",
    "registration_ended": "Registration has ended",
    "registration_not_started": "Registration is not available yet",
    "registration_full": "Event is full"

  },
  "school": {
    "label": "Educational institutions",
    "institutions": "Study places",
    "location": "Location",
    "name": "School Name",
    "institution_type": "Type of educational institution",
    "institution_select_type": "Select the type of institution first",
    "institution_sublevel": "The lower secondary school level",
    "language": "The language of instruction",
    "ownership": "Form of ownership",
    "available_dormitory": "Student home / dormitory available",
    "dormitory": "Student home",
    "special_needs_short": "HEV",
    "special_needs_long": "Special Educational Needs",
    "list": "List",
    "map": "Map",
    "no_result": "Educational institutions meeting the search criteria were not found",
    "legal_address": "Legal address",
    "defacto_address": "Location of operation",
    "website": "Website",
    "contact_info": "Contact Info",
    "contact": "Contact",
    "register_code_short": "Reg. code",
    "available": "Available",
    "unavailable": "None",
    "register_code": "Register code",
    "institution_ownership": "Ownership type",
    "support_projects": "Support projects",
    "investment_measure" : "Investment measure",
    "investment_deadline_year":"Implementation year",
    "investment_deadline": "Implementation deadline",
    "investment_project": "Project",
    "investment_max_amount": "Maximum amount",
    "investment_amount_million_short": "MM",
    "investment_amount_thousand_short": "K",
    "municipalities": "Municipalities",
    "municipalities_detailed": "Towns/districts",
    "counties": "Counties",
    "select_investment_measure_year": "Choose investment measure year",
    "selected_year_investment_measure": "year's investment measure"
  },
  "studyProgramme": {
    "label": "Specialties",
    "level": "Level of curriculum",
    "accreditation": "Accreditation",
    "valid_accreditation": "Valid accreditation",
    "accreditation_decision": "Accreditation decision",
    "accreditation_decision_till": "Accreditation decision due",
    "languages": "Teaching languages",
    "study_duration": "Duration of the course",
    "study_group": "Curriculum Group",
    "admission_status": "Receive status",
    "filter_title": "Specialty",
    "filter_type": "Specialty type",
    "filter_language": "The language of instruction",
    "filter_school": "educational institution",
    "filter_location": "Location",
    "filter_iscedf_broad": "Field of study",
    "filter_iscedf_narrow": "Learning direction",
    "filter_iscedf_detailed": "Curriculum Group",
    "filter_open_admission": "Only open to reception",
    "no_results": "No Search Results",
    "related_label": "Related study programmes",
    "related_filter_location": "Search by location",
    "related_no_results": "No related study programmes",
    "compare_modal_title": "Study programme comparison",
    "compare_modal_content": "<p>Maximum capacity reached.</p><p>You can only add 3 study programmes to comparison.</ p>",
    "compare_modal_close": "Close window",
    "school": "School",
    "degree_or_diploma": "Degree or diploma",
    "specialization": "Specialization",
    "study_capacity": "Capacity",
    "internship_capacity": "Internship capacity",
    "nominal_time": "Nominal time",
    "non_active": "Course not active",
    "added_to_comparison": "Programme added to comparison"
  },
  "login": {
    "username": "Username",
    "password": "Password",
    "error": "Login failed. Please check your username and password.",
    "success": "Successful login"
  },
  "time": {
    "january": "January",
    "february": "February",
    "march": "March",
    "april": "April",
    "may": "May",
    "june": "June",
    "july": "July",
    "august": "August",
    "september": "September",
    "october": "October",
    "november": "November",
    "december": "December",
    "monday": "Monday",
    "monday_short": "M",
    "tuesday": "Tuesday",
    "tuesday_short": "T",
    "wednesday": "Wednesday",
    "wednesday_short": "W",
    "thursday": "Thursday",
    "thursday_short": "T",
    "friday": "Friday",
    "friday_short": "F",
    "saturday": "Saturday",
    "saturday_short": "S",
    "sunday": "Sunday",
    "sunday_short": "S",
    "date": "Date",
    "date_format": "dd/mm/yyyy",
    "date_period_from": "Start date",
    "date_period_to": "End date",
    "from": "From",
    "to": "Till",
    "duration_year_singular": "Year",
    "duration_year_plural": "Years",
    "duration_month_singular": "Month",
    "duration_month_plural": "Months",
    "time_of_day": "Clock",
    "years": "Years"
  },
  "button": {
    "all": "All",
    "map_closer": "See the map for more",
    "add_to_comparison": "Add to comparison",
    "remove_from_comparison":"Remove from comparison",
    "search": "Search",
    "search_from_page": "Search from page",
    "search_detailed": "Advanced Search",
    "search_detailed_short": "Exact",
    "search_brief": "Narrow search",
    "search_brief_short": "Narrow",
    "search_people": "Search people",
    "load_more": "Download More",
    "read_more": "Read more",
    "show_all": "Show All",
    "view_all": "View All",
    "view_more": "View More",
    "filter": "Filter",
    "filter_close": "Close the filter",
    "register": "Register",
    "calendar_add": "Add to calendar",
    "newsletter_submit": "Confirm order",
    "login": "Log in",
    "logout": "Log out",
    "search_close": "",
    "select_type": "",
    "see_comparison": "See comparison",
    "add_to_favourites_label": "Favourites",
    "add_to_favourites_add": "Add to favourites",
    "add_to_favourites_add_success": "Successfully added to favourites",
    "add_to_favourites_remove": "Remove from favourites",
    "add_to_favourites_remove_success": "Successfully removed from favourites",
    "add_to_favourites_title": "Title",
    "back": "Back",
    "back_to_dashboard":"Back to dashboard",
    "save": "Save",
    "submit": "Submit",
    "edit": "Edit",
    "continue": "Continue",
    "previous": "Previous",
    "next": "Next",
    "yes": "Yes",
    "cancel": "Cancel"
    
  },
  "tooltip": {
    "share": "Share page",
    "favourites": "Add as a favourite"
  },
  "notFound": {
    "explanation": "It looks like the page you were looking for was not found. <br> Error code: <b> 404 </b>"
  },
  "errors": {
    "enter_valid_date": "Enter valid date",
    "personal_data_request": "Apologies. There was a technical error reading data from the Estonian Education Infosystem. Try again later.",
    "personal_data_missing": "Relevant data missing from the Estonian Education Infosystem.",
    "studies_data_request": "Apologies. There was a technical error reading data from the Estonian Education Infosystem. Try again later.",
    "studies_data_missing": "Relevant data missing from the Estonian Education Infosystem.",
    "teachings_data_request": "Apologies. There was a technical error reading data from the Estonian Education Infosystem. Try again later.",
    "teachings_data_missing": "Relevant data missing from the Estonian Education Infosystem."
  },
  "search": {
    "label": "Search",
    "results": "Search results",
    "keyword": "Keyword",
    "no_results_start": "Matching results for keyword",
    "no_results_end": "not found.<br> Try a different query.",
    "filter_results": "Filter results"
  }
}
